[
  {
    "title": "Get started",
    "href": "#getStarted"
  },
  {
    "title": "Features",
    "href": "#features",
    "submenu": [
      {
        "title": "Campaign Kit",
        "links": [
          {
            "title": "Discovery Mode",
            "href": "#features/campaign-kit/discovery-mode"
          },
          { "title": "Marquee", "href": "#features/campaign-kit/marquee" },
          {
            "title": "Playlisting",
            "href": "#features/campaign-kit/playlisting"
          },
          { "title": "Showcase", "href": "#features/campaign-kit/showcase" }
        ]
      },
      {
        "title": "Video & Visuals",
        "links": [
          {
            "title": "Artist profile",
            "href": "#features/video-visuals/artist-profile"
          },
          { "title": "Canvas", "href": "#features/video-visuals/canvas" },
          {
            "title": "Countdown Pages",
            "href": "#features/video-visuals/countdown-pages"
          },
          { "title": "Clips", "href": "#features/video-visuals/clips" },
          {
            "title": "Music videos",
            "href": "#features/video-visuals/music-videos"
          }
        ]
      },
      {
        "title": "Merch, Live & More",
        "links": [
          {
            "title": "Fan Support",
            "href": "#features/merch-live/fan-support"
          },
          {
            "title": "Live events",
            "href": "#features/merch-live/live-events"
          },
          { "title": "Merch", "href": "#features/merch-live/merch" }
        ]
      },
      {
        "title": "Analytics",
        "links": [
          { "title": "Segments", "href": "#features/analytics/segments" }
        ]
      }
    ]
  },
  {
    "title": "Resources",
    "href": "#resources"
  },
  {
    "title": "Help",
    "href": "#help"
  }
]
